intreehooks.py
intreehooks-1.0.dist-info/DESCRIPTION.rst
intreehooks-1.0.dist-info/METADATA
intreehooks-1.0.dist-info/RECORD
intreehooks-1.0.dist-info/WHEEL
intreehooks-1.0.dist-info/metadata.json
intreehooks-1.0.dist-info/top_level.txt
