Metadata-Version: 2.0
Name: intreehooks
Version: 1.0
Summary: Load a PEP 517 backend from inside the source tree
Home-page: https://github.com/takluyver/intreehooks
Author: Thomas Kluyver
Author-email: thomas@kluyver.me.uk
License: UNKNOWN
Platform: UNKNOWN
Classifier: Intended Audience :: Developers
Classifier: License :: OSI Approved :: MIT License
Classifier: Topic :: Software Development :: Libraries :: Python Modules
Requires-Dist: pytoml
